odoo/addons/stock_inventory_preparation_filter/README.rst
odoo/addons/stock_inventory_preparation_filter/__init__.py
odoo/addons/stock_inventory_preparation_filter/__manifest__.py
odoo/addons/stock_inventory_preparation_filter/i18n/am.po
odoo/addons/stock_inventory_preparation_filter/i18n/ar.po
odoo/addons/stock_inventory_preparation_filter/i18n/bg.po
odoo/addons/stock_inventory_preparation_filter/i18n/bs.po
odoo/addons/stock_inventory_preparation_filter/i18n/ca.po
odoo/addons/stock_inventory_preparation_filter/i18n/cs.po
odoo/addons/stock_inventory_preparation_filter/i18n/cs_CZ.po
odoo/addons/stock_inventory_preparation_filter/i18n/da.po
odoo/addons/stock_inventory_preparation_filter/i18n/de.po
odoo/addons/stock_inventory_preparation_filter/i18n/el_GR.po
odoo/addons/stock_inventory_preparation_filter/i18n/en_GB.po
odoo/addons/stock_inventory_preparation_filter/i18n/es.po
odoo/addons/stock_inventory_preparation_filter/i18n/es_AR.po
odoo/addons/stock_inventory_preparation_filter/i18n/es_CL.po
odoo/addons/stock_inventory_preparation_filter/i18n/es_CO.po
odoo/addons/stock_inventory_preparation_filter/i18n/es_CR.po
odoo/addons/stock_inventory_preparation_filter/i18n/es_DO.po
odoo/addons/stock_inventory_preparation_filter/i18n/es_EC.po
odoo/addons/stock_inventory_preparation_filter/i18n/es_ES.po
odoo/addons/stock_inventory_preparation_filter/i18n/es_MX.po
odoo/addons/stock_inventory_preparation_filter/i18n/es_PE.po
odoo/addons/stock_inventory_preparation_filter/i18n/es_PY.po
odoo/addons/stock_inventory_preparation_filter/i18n/es_VE.po
odoo/addons/stock_inventory_preparation_filter/i18n/et.po
odoo/addons/stock_inventory_preparation_filter/i18n/eu.po
odoo/addons/stock_inventory_preparation_filter/i18n/fa.po
odoo/addons/stock_inventory_preparation_filter/i18n/fi.po
odoo/addons/stock_inventory_preparation_filter/i18n/fr.po
odoo/addons/stock_inventory_preparation_filter/i18n/fr_CA.po
odoo/addons/stock_inventory_preparation_filter/i18n/fr_CH.po
odoo_addon_stock_inventory_preparation_filter-18.0.1.0.0.2.dist-info/METADATA
odoo_addon_stock_inventory_preparation_filter-18.0.1.0.0.2.dist-info/WHEEL
odoo_addon_stock_inventory_preparation_filter-18.0.1.0.0.2.dist-info/top_level.txt
odoo_addon_stock_inventory_preparation_filter-18.0.1.0.0.2.dist-info/RECORD
